{"inkVersion":21,"root":[["\n","\n",{"->":"main"},["done",{"#f":5,"#n":"g-0"}],null],"done",{"main":[["ev",{"x()":"CheckMelancholy"},20,"<=","/ev",{"->":".^.b","c":true},{"b":["\n",{"->":"TrueEnd"},{"->":"main.3"},null]}],["ev",{"x()":"CheckMelancholy"},20,">",{"x()":"CheckMelancholy"},80,"<=","&&","/ev",{"->":".^.b","c":true},{"b":["\n",{"->":"NormalEnd"},{"->":"main.3"},null]}],["ev",{"x()":"CheckMelancholy"},80,">","/ev",{"->":".^.b","c":true},{"b":["\n",{"->":"BadEnd"},{"->":"main.3"},null]}],"nop","\n","end",{"#f":1}],"TrueEnd":["ev","str","^true","/str",{"x()":"ChangeEndingBGM","exArgs":1},"pop","/ev","\n","#","^speaker: Layne ","/#","#","^portrait: Layne ","/#","#","^layout: left","/#","^我想起來了！只要......","\n","#","^speaker: 腦內的聲音 ","/#","#","^portrait: Narrator ","/#","#","^layout: left","/#","^（你的腦袋飛快地運轉，將當初你放置在那還沒有安裝的部件，使用從前對於藍圖線路的記憶拼接起來。）","\n","#","^speaker: Layne ","/#","#","^portrait: Layne ","/#","#","^layout: left","/#","^完成了！","\n","#","^speaker: Skyler ","/#","#","^portrait: Skyler ","/#","#","^layout: right","/#","^太好了！那我們準備出發吧。","\n","#","^speaker: 潛水艇 ","/#","#","^portrait: Narrator ","/#","#","^layout: right","/#","^系統已經安裝完成，自動駕駛模式已啟動，目的地：……。","\n","ev","str","^Credits","/str",{"x()":"ChangeScene","exArgs":1},"pop","/ev","\n","done",{"#f":1}],"NormalEnd":["ev","str","^normal","/str",{"x()":"ChangeEndingBGM","exArgs":1},"pop","/ev","\n","#","^speaker: Layne ","/#","#","^portrait: Layne ","/#","#","^layout: left","/#","^抱歉，我想了想還是想不起來。","\n","#","^speaker: Skyler ","/#","#","^portrait: Skyler ","/#","#","^layout: right","/#","^真的想不起來嗎？那就頭大了.....。","\n","#","^speaker: Layne ","/#","#","^portrait: Layne ","/#","#","^layout: left","/#","^而且通往原本潛水艇的路線已經被封閉了。","\n","#","^speaker: Skyler ","/#","#","^portrait: Skyler ","/#","#","^layout: right","/#","^看來只能找尋另外一條能夠回去的路了呢......。","\n","done",{"#f":1}],"BadEnd":["ev","str","^bad","/str",{"x()":"ChangeEndingBGM","exArgs":1},"pop","/ev","\n","#","^speaker: 腦內的聲音 ","/#","#","^portrait: Narrator ","/#","#","^layout: left","/#","^（你選擇衝出艙門一把抓住 Rene ，但此時海水保護模式已經關閉。）","\n","#","^speaker: Skyler ","/#","#","^portrait: Skyler ","/#","#","^layout: right","/#","^Layne！！你在做什麼！！","\n","#","^speaker: 腦內的聲音 ","/#","#","^portrait: Narrator ","/#","#","^layout: left","/#","^（Skyler 衝去想將艙門關閉，然而海水此時灌進了潛水艇，潛水艇內部的設備因此損壞，進而引發爆炸。）","\n","#","^speaker: 腦內的聲音 ","/#","#","^portrait: Narrator ","/#","#","^layout: left","/#","^（由於你距離潛艇並不遠，因此你的身體也被炸傷。）","\n","#","^speaker: Layne ","/#","#","^portrait: Layne ","/#","#","^layout: left","/#","^Rene，我這次不會再像之前一樣對你棄之不顧了.......。","\n","#","^speaker: Rene ","/#","#","^portrait: Rene ","/#","#","^layout: right","/#","^謝謝你，這樣我們就能夠永遠在一起了呢。","\n","done",{"#f":1}],"Find4items":["ev",{"VAR?":"getDivingMask"},{"VAR?":"getOxygenTank"},"&&",{"VAR?":"getWetsuit"},"&&",{"VAR?":"getUnderwaterCamera"},"&&","/ev",[{"->":".^.b","c":true},{"b":["\n","#","^speaker: Layne ","/#","#","^portrait: Layne ","/#","#","^layout: left","/#","^要搬上潛水艇的物資都找齊了，現在前往碼頭與「逆行者」隊員們會合吧。","\n","ev","str","^前往碼頭尋找「逆行者」隊長報到","/str",{"x()":"ShowMission","exArgs":1},"pop","/ev","\n",{"->":".^.^.^.10"},null]}],"nop","\n","done",{"#f":1}],"CheakPillars":["ev",{"VAR?":"pillarA"},4,"%",2,"==",{"VAR?":"pillarB"},4,"%",2,"==","&&",{"VAR?":"pillarC"},4,"%",0,"==","&&",{"VAR?":"pillarD"},4,"%",2,"==","&&","/ev",[{"->":".^.b","c":true},{"b":["\n","ev","str","^click","/str",{"x()":"PlaySound","exArgs":1},"pop","/ev","\n","#","^speaker: 腦內的聲音 ","/#","#","^portrait: default ","/#","#","^layout: left","/#","^洞穴的深處傳來了動靜。","\n","ev",1,"/ev",{"VAR=":"completePillars","re":true},"ev",{"x()":"DeleteStone"},"pop","/ev","\n",{"->":".^.^.^.26"},null]}],"nop","\n","done",{"#f":1}],"global decl":["ev",false,{"VAR=":"passwordForWarehouse"},false,{"VAR=":"getDivingMask"},false,{"VAR=":"getOxygenTank"},false,{"VAR=":"getWetsuit"},false,{"VAR=":"getUnderwaterCamera"},true,{"VAR=":"firstMeetWorkaholic"},false,{"VAR=":"getCleaner"},false,{"VAR=":"getPreciousMaterials"},false,{"VAR=":"hasTriggeredFindCleaner"},false,{"VAR=":"hasTriggeredFindPreciousMaterials"},true,{"VAR=":"firstMeetReligiousManiac"},false,{"VAR=":"getReligiousBooks"},false,{"VAR=":"hasSawStrangeSymbols"},false,{"VAR=":"hasAskSymbols"},1024,{"VAR=":"pillarA"},1024,{"VAR=":"pillarB"},1024,{"VAR=":"pillarC"},1024,{"VAR=":"pillarD"},0,{"VAR=":"completePillars"},false,{"VAR=":"passwordOnWall"},false,{"VAR=":"hasSawPasswordDoor"},false,{"VAR=":"hasRotatePillar"},false,{"VAR=":"getBasementKey"},false,{"VAR=":"getBlueprint"},3,{"VAR=":"t"},"/ev","end",null],"#f":1}],"listDefs":{}}